fivc/__about__.py
fivc/__init__.py
fivc/cli.py
fivc/core/__init__.py
fivc/core/fixtures/configs_basics.yml
fivc/core/fixtures/configs_loggers.yml
fivc/core/implements/__init__.py
fivc/core/implements/caches_mem.py
fivc/core/implements/caches_redis.py
fivc/core/implements/configs_jsonfile.py
fivc/core/implements/configs_yamlfile.py
fivc/core/implements/loggers_builtin.py
fivc/core/implements/mutexes_redis.py
fivc/core/implements/utils.py
fivc/core/interfaces/__init__.py
fivc/core/interfaces/caches.py
fivc/core/interfaces/configs.py
fivc/core/interfaces/loggers.py
fivc/core/interfaces/modules.py
fivc/core/interfaces/mutexes.py
fivc/core/interfaces/utils.py
fivc-0.1.1.dist-info/METADATA
fivc-0.1.1.dist-info/WHEEL
fivc-0.1.1.dist-info/entry_points.txt
fivc-0.1.1.dist-info/RECORD
