Metadata-Version: 2.4
Name: fivc
Version: 0.1.1
Summary: FIVC - Five Component Framework: 轻量级Python组件管理框架
Project-URL: Homepage, https://github.com/5C-Plus/fivc
Project-URL: Documentation, https://github.com/5C-Plus/fivc#readme
Project-URL: Repository, https://github.com/5C-Plus/fivc.git
Project-URL: Issues, https://github.com/5C-Plus/fivc/issues
Project-URL: Changelog, https://github.com/5C-Plus/fivc/blob/main/CHANGELOG.md
Author-email: Charlie ZHANG <sunnypig2002@gmail.com>
Maintainer-email: Charlie ZHANG <sunnypig2002@gmail.com>
License: MIT
Keywords: component,configuration,dependency-injection,framework,ioc
Classifier: Development Status :: 4 - Beta
Classifier: Intended Audience :: Developers
Classifier: License :: OSI Approved :: MIT License
Classifier: Operating System :: OS Independent
Classifier: Programming Language :: Python
Classifier: Programming Language :: Python :: 3.8
Classifier: Programming Language :: Python :: 3.9
Classifier: Programming Language :: Python :: 3.10
Classifier: Programming Language :: Python :: 3.11
Classifier: Programming Language :: Python :: 3.12
Classifier: Programming Language :: Python :: Implementation :: CPython
Classifier: Programming Language :: Python :: Implementation :: PyPy
Classifier: Topic :: Software Development :: Libraries :: Application Frameworks
Classifier: Topic :: Software Development :: Libraries :: Python Modules
Requires-Python: >=3.8.1
Requires-Dist: pyyaml>=6.0.1
Provides-Extra: all
Requires-Dist: black>=23.0.0; extra == 'all'
Requires-Dist: fastapi>=0.100.0; extra == 'all'
Requires-Dist: isort>=5.12.0; extra == 'all'
Requires-Dist: mkdocs-material>=9.0.0; extra == 'all'
Requires-Dist: mkdocs>=1.5.0; extra == 'all'
Requires-Dist: mkdocstrings[python]>=0.22.0; extra == 'all'
Requires-Dist: mypy>=1.0.0; extra == 'all'
Requires-Dist: pre-commit>=3.0.0; extra == 'all'
Requires-Dist: pytest-asyncio>=0.21.0; extra == 'all'
Requires-Dist: pytest-cov>=4.0.0; extra == 'all'
Requires-Dist: pytest>=7.0.0; extra == 'all'
Requires-Dist: redis>=4.5.0; extra == 'all'
Requires-Dist: ruff>=0.0.243; extra == 'all'
Requires-Dist: sqlalchemy>=2.0.0; extra == 'all'
Requires-Dist: sqlmodel>=0.0.21; extra == 'all'
Provides-Extra: dev
Requires-Dist: black>=23.0.0; extra == 'dev'
Requires-Dist: isort>=5.12.0; extra == 'dev'
Requires-Dist: mypy>=1.0.0; extra == 'dev'
Requires-Dist: pre-commit>=3.0.0; extra == 'dev'
Requires-Dist: pytest-cov>=4.0.0; extra == 'dev'
Requires-Dist: pytest>=7.0.0; extra == 'dev'
Requires-Dist: ruff>=0.0.243; extra == 'dev'
Provides-Extra: docs
Requires-Dist: mkdocs-material>=9.0.0; extra == 'docs'
Requires-Dist: mkdocs>=1.5.0; extra == 'docs'
Requires-Dist: mkdocstrings[python]>=0.22.0; extra == 'docs'
Provides-Extra: extra
Requires-Dist: fastapi>=0.100.0; extra == 'extra'
Requires-Dist: redis>=4.5.0; extra == 'extra'
Requires-Dist: sqlalchemy>=2.0.0; extra == 'extra'
Requires-Dist: sqlmodel>=0.0.21; extra == 'extra'
Provides-Extra: test
Requires-Dist: pytest-asyncio>=0.21.0; extra == 'test'
Requires-Dist: pytest-cov>=4.0.0; extra == 'test'
Requires-Dist: pytest>=7.0.0; extra == 'test'
